alibabacloud_ddoscoo20200101/__init__.py
alibabacloud_ddoscoo20200101/client.py
alibabacloud_ddoscoo20200101/models/__init__.py
alibabacloud_ddoscoo20200101/models/_add_auto_cc_blacklist_request.py
alibabacloud_ddoscoo20200101/models/_add_auto_cc_blacklist_response.py
alibabacloud_ddoscoo20200101/models/_add_auto_cc_blacklist_response_body.py
alibabacloud_ddoscoo20200101/models/_add_auto_cc_whitelist_request.py
alibabacloud_ddoscoo20200101/models/_add_auto_cc_whitelist_response.py
alibabacloud_ddoscoo20200101/models/_add_auto_cc_whitelist_response_body.py
alibabacloud_ddoscoo20200101/models/_associate_web_cert_request.py
alibabacloud_ddoscoo20200101/models/_associate_web_cert_response.py
alibabacloud_ddoscoo20200101/models/_associate_web_cert_response_body.py
alibabacloud_ddoscoo20200101/models/_attach_scene_defense_object_request.py
alibabacloud_ddoscoo20200101/models/_attach_scene_defense_object_response.py
alibabacloud_ddoscoo20200101/models/_attach_scene_defense_object_response_body.py
alibabacloud_ddoscoo20200101/models/_config_domain_security_profile_request.py
alibabacloud_ddoscoo20200101/models/_config_domain_security_profile_response.py
alibabacloud_ddoscoo20200101/models/_config_domain_security_profile_response_body.py
alibabacloud_ddoscoo20200101/models/_config_l7global_rule_request.py
alibabacloud_ddoscoo20200101/models/_config_l7global_rule_response.py
alibabacloud_ddoscoo20200101/models/_config_l7global_rule_response_body.py
alibabacloud_ddoscoo20200101/models/_config_l7rs_policy_request.py
alibabacloud_ddoscoo20200101/models/_config_l7rs_policy_response.py
alibabacloud_ddoscoo20200101/models/_config_l7rs_policy_response_body.py
alibabacloud_ddoscoo20200101/models/_config_l7us_keepalive_request.py
alibabacloud_ddoscoo20200101/models/_config_l7us_keepalive_response.py
alibabacloud_ddoscoo20200101/models/_config_l7us_keepalive_response_body.py
alibabacloud_ddoscoo20200101/models/_config_layer_4real_limit_request.py
alibabacloud_ddoscoo20200101-4.0.0.dist-info/LICENSE
alibabacloud_ddoscoo20200101-4.0.0.dist-info/METADATA
alibabacloud_ddoscoo20200101-4.0.0.dist-info/WHEEL
alibabacloud_ddoscoo20200101-4.0.0.dist-info/top_level.txt
alibabacloud_ddoscoo20200101-4.0.0.dist-info/RECORD
